TextInParseX/TextInParseX.py
TextInParseX/__init__.py
tests/__init__.py
tests/test_parseX.py
tests/test_parseX2.py
TextInParseX_test-1.0.0.dist-info/METADATA
TextInParseX_test-1.0.0.dist-info/WHEEL
TextInParseX_test-1.0.0.dist-info/top_level.txt
TextInParseX_test-1.0.0.dist-info/RECORD
