Metadata-Version: 2.1
Name: TextInParseX-test
Version: 1.0.0
Summary: A text-in parser engine for pdf to markdown processing
Home-page: https://github.com/intsig-textin/parsex-sdk
Author: bin_zhang
License: UNKNOWN
Platform: UNKNOWN
Classifier: Programming Language :: Python :: 3
Classifier: License :: OSI Approved :: MIT License
Classifier: Operating System :: OS Independent
Requires-Python: >=3.6
Requires-Dist: opencv-python-headless
Requires-Dist: numpy
Requires-Dist: requests
